hardwario/__init__.py
hardwario/__main__.py
hardwario/chester/__init__.py
hardwario/chester/cli/__init__.py
hardwario/chester/cli/app.py
hardwario/chester/cli/lte.py
hardwario/chester/cli/validate.py
hardwario/chester/connector.py
hardwario/chester/coredump.py
hardwario/chester/firmwareapi.py
hardwario/chester/nrfjprog.py
hardwario/chester/pib.py
hardwario/chester/utils.py
hardwario/cli.py
hardwario/common/__init__.py
hardwario/common/mqtt_client.py
hardwario/common/pib.py
hardwario/common/utils.py
hardwario/device/__init__.py
hardwario/device/cli.py
hardwario/device/connector/__init__.py
hardwario/device/connector/mqtt.py
hardwario/device/nrfjprog.py
hardwario/resources/__init__.py
hardwario/resources/nrf91_disable_ap_protect.hex
hardwario-1.6.6.dist-info/LICENSE
hardwario-1.6.6.dist-info/METADATA
hardwario-1.6.6.dist-info/WHEEL
hardwario-1.6.6.dist-info/entry_points.txt
hardwario-1.6.6.dist-info/RECORD
