Metadata-Version: 2.3
Name: hardwario
Version: 1.6.6
Summary: HARDWARIO Command Line Tool
License: MIT
Author: Karel Blavka
Author-email: karel.blavka@hardwario.com
Requires-Python: >=3.9,<4
Classifier: Development Status :: 5 - Production/Stable
Classifier: Environment :: Console
Classifier: License :: OSI Approved :: MIT License
Classifier: Operating System :: OS Independent
Classifier: Programming Language :: Python :: 3
Classifier: Programming Language :: Python :: 3.9
Classifier: Programming Language :: Python :: 3.10
Classifier: Programming Language :: Python :: 3.11
Classifier: Programming Language :: Python :: 3.12
Classifier: Programming Language :: Python :: 3.13
Classifier: Topic :: Software Development :: Libraries :: Python Modules
Classifier: Topic :: Utilities
Requires-Dist: certifi (>=2025.8.3,<2026.0.0)
Requires-Dist: click (>=8.1.8,<9.0.0)
Requires-Dist: loguru (>=0.7.3,<0.8.0)
Requires-Dist: paho-mqtt (>=2.1.0,<3.0.0)
Requires-Dist: prompt-toolkit (>=3.0.51,<4.0.0)
Requires-Dist: pylink-square (>=1.6.0,<2.0.0)
Requires-Dist: pynrfjprog (>=10.24.2,<11.0.0)
Requires-Dist: requests (>=2.32.4,<3.0.0)
Requires-Dist: rttt (>=1.3.3,<2.0.0)
Requires-Dist: tomli-w (>=1.2.0,<2.0.0)
Requires-Dist: urllib3 (>=2.5.0,<3.0.0)
Project-URL: Homepage, https://github.com/hardwario/py-hardwario
Project-URL: Repository, https://github.com/hardwario/py-hardwario
